<annotation>
	<filename>32280.jpg</filename>
	<size>
		<width>1280</width>
		<height>720</height>
		<depth>3</depth>
	</size>
	<object>
		<name>weed</name>
		<bndbox>
			<xmin>360</xmin>
			<ymin>478</ymin>
			<xmax>416</xmax>
			<ymax>514</ymax>
		</bndbox>
	</object>
	<object>
		<name>weed</name>
		<bndbox>
			<xmin>1196</xmin>
			<ymin>477</ymin>
			<xmax>1255</xmax>
			<ymax>510</ymax>
		</bndbox>
	</object>
	<object>
		<name>weed</name>
		<bndbox>
			<xmin>956</xmin>
			<ymin>535</ymin>
			<xmax>1025</xmax>
			<ymax>589</ymax>
		</bndbox>
	</object>
	<object>
		<name>weed</name>
		<bndbox>
			<xmin>235</xmin>
			<ymin>30</ymin>
			<xmax>268</xmax>
			<ymax>97</ymax>
		</bndbox>
	</object>
	<object>
		<name>weed</name>
		<bndbox>
			<xmin>416</xmin>
			<ymin>667</ymin>
			<xmax>446</xmax>
			<ymax>685</ymax>
		</bndbox>
	</object>
</annotation>